smartwrappers/__init__.py
smartwrappers/constants.py
smartwrappers-0.0.5.dist-info/LICENSE
smartwrappers-0.0.5.dist-info/METADATA
smartwrappers-0.0.5.dist-info/WHEEL
smartwrappers-0.0.5.dist-info/top_level.txt
smartwrappers-0.0.5.dist-info/RECORD
