Metadata-Version: 2.1
Name: smartwrappers
Version: 0.0.5
Summary: A Python 3 library to manipulate objects with shared mutable wrappers
Home-page: https://github.com/mavedev/SmartWrappers
Author: Cirill Usatchoff (Kyrylo Usachov)
Author-email: usatchoff@gmail.com
License: UNKNOWN
Platform: UNKNOWN
Classifier: Programming Language :: Python :: 3
Classifier: License :: OSI Approved :: MIT License
Classifier: Operating System :: OS Independent
Requires-Python: >=3.6
